mcppp/__init__.py
mcppp/main.py
mcppp-0.4.0.dist-info/METADATA
mcppp-0.4.0.dist-info/WHEEL
mcppp-0.4.0.dist-info/entry_points.txt
mcppp-0.4.0.dist-info/RECORD
